LICENSE
MANIFEST.in
README.md
setup.cfg
setup.py
versioneer.py
shortcutter/__init__.py
shortcutter/_version.py
shortcutter/base.py
shortcutter/exception.py
shortcutter/linux.py
shortcutter/macos.py
shortcutter/windows.py
shortcutter.egg-info/PKG-INFO
shortcutter.egg-info/SOURCES.txt
shortcutter.egg-info/dependency_links.txt
shortcutter.egg-info/entry_points.txt
shortcutter.egg-info/not-zip-safe
shortcutter.egg-info/requires.txt
shortcutter.egg-info/top_level.txt