Metadata-Version: 2.1
Name: shortcutter
Version: 0.1.21
Summary: Easy cross-platform creation of shortcuts supporting virtual and Anaconda environments (fork of Shortcut)
Home-page: https://github.com/kiwi0fruit/shortcutter
Author: Martin O'Hanlon, Peter Zagubisalo
Author-email: peter.zagubisalo@gmail.com
License: MIT
Platform: UNKNOWN
Classifier: Development Status :: 3 - Alpha
Classifier: Intended Audience :: End Users/Desktop
Classifier: Topic :: Desktop Environment
Classifier: License :: OSI Approved :: MIT License
Classifier: Programming Language :: Python :: 2
Classifier: Programming Language :: Python :: 2.7
Classifier: Programming Language :: Python :: 3
Classifier: Programming Language :: Python :: 3.3
Classifier: Programming Language :: Python :: 3.4
Classifier: Programming Language :: Python :: 3.5
Classifier: Programming Language :: Python :: 3.6
Classifier: Environment :: MacOS X
Classifier: Environment :: Win32 (MS Windows)
